ial_expertise/__init__.py
ial_expertise/task.py
ial_expertise/cli/fields_expertise_get.py
ial_expertise/cli/fields_expertise_plot.py
ial_expertise/drhook/drhook_merge_walltime_ave.pl
ial_expertise/drhook/drhook_merge_walltime_max.pl
ial_expertise/experts/__init__.py
ial_expertise/experts/assim.py
ial_expertise/experts/build.py
ial_expertise/experts/fields.py
ial_expertise/experts/norms.py
ial_expertise/experts/oops.py
ial_expertise/experts/profiling.py
ial_expertise/experts/setup.py
ial_expertise/experts/thresholds.py
ial_expertise/experts/util.py
ial_expertise-1.3.2.dist-info/licenses/LICENSE
ial_expertise-1.3.2.dist-info/METADATA
ial_expertise-1.3.2.dist-info/WHEEL
ial_expertise-1.3.2.dist-info/entry_points.txt
ial_expertise-1.3.2.dist-info/top_level.txt
ial_expertise-1.3.2.dist-info/RECORD
