Metadata-Version: 2.4
Name: ial_expertise
Version: 1.3.2
Summary: IAL expertise: Experts tools to analyse the outputs of IAL configurations.
Author-email: Alexandre Mary <alexandre.mary@meteo.fr>
License: CECILL-C
Project-URL: source, https://github.com/ACCORD-NWP/IAL-expertise.git
Project-URL: tracker, https://github.com/ACCORD-NWP/IAL-expertise/issues
Keywords: IAL,DAVAI
Requires-Python: >=3.7
License-File: LICENSE
Requires-Dist: footprints
Requires-Dist: numpy
Requires-Dist: arpifs_listings>=1.2.2
Requires-Dist: taylorism
Provides-Extra: all
Requires-Dist: epygram; extra == "all"
Requires-Dist: matplotlib; extra == "all"
Provides-Extra: graphics
Requires-Dist: matplotlib; extra == "graphics"
Dynamic: license-file
